LICENSE.txt
MANIFEST.in
README
README.rst
README.txt
pypi_get_stat.py
pypi_graph_stat.py
setup.py
pypi_stat.egg-info/PKG-INFO
pypi_stat.egg-info/SOURCES.txt
pypi_stat.egg-info/dependency_links.txt
pypi_stat.egg-info/requires.txt
pypi_stat.egg-info/top_level.txt