Metadata-Version: 1.1
Name: pypi-stat
Version: 1.3.2
Summary: solution for getting packages stat, and graphing them
Home-page: https://github.com/jul/pypi-stat
Author: Julien Tayon
Author-email: julien@tayon.net
License: PYTHON SOFTWARE FOUNDATION LICENSE VERSION 2
Platform: UNKNOWN
Classifier: Development Status :: 5 - Production/Stable
Classifier: Intended Audience :: Developers
Classifier: License :: OSI Approved :: Python Software Foundation License
Classifier: Programming Language :: Python :: 2.6
Classifier: Operating System :: OS Independent
Classifier: Programming Language :: Python :: 2.7
Classifier: Programming Language :: Python
